Metadata-Version: 1.1
Name: tidyextractors
Version: 0.3.4
Summary: A collection of tools for extracting data into tidy DataFrames.
Home-page: https://github.com/networks-lab/tidyextractors/
Author: networks-lab
Author-email: john.mclevey@uwaterloo.ca
License: GPLv3
Download-URL: https://github.com/networks-lab/tidyextractors/archive/0.3.4.tar.gz
Keywords: Git Twitter Pandas Tidy Data mbox
Platform: UNKNOWN
Classifier: Development Status :: 1 - Planning
Classifier: License :: OSI Approved :: GNU General Public License v3 (GPLv3)
Classifier: Programming Language :: Python :: 3.4
Classifier: Intended Audience :: Science/Research
Classifier: Topic :: Scientific/Engineering :: Information Analysis
Classifier: Topic :: Scientific/Engineering :: Mathematics
Classifier: Topic :: Sociology
Classifier: Topic :: Software Development :: Version Control :: Git
